Metadata-Version: 2.1
Name: vagas-cfs
Version: 0.2
Summary: Conversor utilizado para a geração do Relatório de Vagas dos CFS
Author: Gabriel Ernesto Barboza Pereira
Author-email: ernesto.gabriel@pucpr.br
License: MIT
Keywords: conversor vagas_cfs
License-File: LICENSE.txt
